{
  "mapId": "s04b_nb2",
  "version": 1,
  "floorCollision": {
    "yTolerance": 0.25,
    "excludedMeshPatterns": [],
    "triangles": {}
  },
  "portals": [
    {
      "id": "portal_1770758491430_kxga3o6k2",
      "direction": "south",
      "position": [
        -0.3582059577199772,
        0,
        20.776940483086953
      ],
      "label": "south"
    }
  ],
  "textureFixes": [
    {
      "textureFile": "s04_0_kaidan.png",
      "meshNames": [
        "s04b_nb2_m_4"
      ],
      "repeatX": 2,
      "repeatY": 1,
      "offsetX": 0,
      "offsetY": 0,
      "wrapS": "mirror"
    }
  ],
  "obstacles": [],
  "lastModified": "2026-02-10T21:21:31.938Z",
  "exportedAt": "2026-02-11T10:31:56.314Z"
}