{
  "mapId": "s06a_ib2",
  "version": 1,
  "floorCollision": {
    "yTolerance": 0.25,
    "excludedMeshPatterns": [],
    "triangles": {}
  },
  "portals": [
    {
      "id": "portal_1770799796195_5hzp5253v",
      "direction": "north",
      "position": [
        0.034089700591139915,
        0,
        -19.841463261974685
      ],
      "label": "north"
    },
    {
      "id": "portal_1770799809133_9n3amgdce",
      "direction": "south",
      "position": [
        -0.05265169764758504,
        0,
        20.01165727843509
      ],
      "label": "south"
    }
  ],
  "textureFixes": [],
  "obstacles": [],
  "lastModified": "2026-02-11T08:50:09.641Z",
  "exportedAt": "2026-02-11T10:00:19.536Z"
}